diveplane/community/__init__.py
diveplane/community/client.py
diveplane/community/lib/__init__.py
diveplane/community/lib/amlg/__init__.py
diveplane/community/lib/amlg/darwin/__init__.py
diveplane/community/lib/amlg/darwin/amd64/__init__.py
diveplane/community/lib/amlg/darwin/amd64/amalgam-mt-noavx.dylib
diveplane/community/lib/amlg/darwin/amd64/amalgam-mt.dylib
diveplane/community/lib/amlg/darwin/amd64/amalgam-omp.dylib
diveplane/community/lib/amlg/darwin/amd64/amalgam-st.dylib
diveplane/community/lib/amlg/darwin/arm64/__init__.py
diveplane/community/lib/amlg/darwin/arm64/amalgam-mt.dylib
diveplane/community/lib/amlg/darwin/arm64/amalgam-omp.dylib
diveplane/community/lib/amlg/darwin/arm64/amalgam-st.dylib
diveplane/community/lib/amlg/linux/__init__.py
diveplane/community/lib/amlg/linux/amd64/__init__.py
diveplane/community/lib/amlg/linux/amd64/amalgam-mt-noavx.so
diveplane/community/lib/amlg/linux/amd64/amalgam-mt.so
diveplane/community/lib/amlg/linux/amd64/amalgam-omp.so
diveplane/community/lib/amlg/linux/amd64/amalgam-st.so
diveplane/community/lib/amlg/linux/arm64/__init__.py
diveplane/community/lib/amlg/linux/arm64/amalgam-mt.so
diveplane/community/lib/amlg/linux/arm64/amalgam-omp.so
diveplane/community/lib/amlg/linux/arm64/amalgam-st.so
diveplane/community/lib/amlg/windows/__init__.py
diveplane/community/lib/amlg/windows/amd64/__init__.py
diveplane/community/lib/amlg/windows/amd64/amalgam-mt-noavx.dll
diveplane/community/lib/amlg/windows/amd64/amalgam-mt.dll
diveplane/community/lib/amlg/windows/amd64/amalgam-omp.dll
diveplane/community/lib/amlg/windows/amd64/amalgam-st.dll
diveplane/community/lib/core/__init__.py
diveplane/community/lib/core/diveplane.caml
diveplane/community/lib/core/trainee_template.caml
diveplane/community/resources/__init__.py
diveplane/community/resources/diveplane.yml
diveplane/community/tests/__init__.py
diveplane/community/tests/test_standalone.py
diveplane_reactor_community-1.0.111.dist-info/LICENSE.txt
diveplane_reactor_community-1.0.111.dist-info/METADATA
diveplane_reactor_community-1.0.111.dist-info/WHEEL
diveplane_reactor_community-1.0.111.dist-info/top_level.txt
diveplane_reactor_community-1.0.111.dist-info/RECORD
