Metadata-Version: 2.1
Name: diveplane-reactor-community
Version: 1.0.111
Summary: Diveplane Reactor and Scikit Estimator for the interpretable Machine Learning and Artificial Intelligence API Diveplane.
Home-page: https://www.diveplane.com
Author: Diveplane Corporation
Author-email: support@diveplane.com
License: Diveplane Corporation Free Software License
Project-URL: Documentation, https://docs.community.diveplane.com/
Keywords: machine learning,artificial intelligence
Classifier: Intended Audience :: Science/Research
Classifier: Topic :: Scientific/Engineering :: Artificial Intelligence
Classifier: License :: Other/Proprietary License
Classifier: Programming Language :: Python :: 3
Classifier: Programming Language :: Python :: 3.8
Classifier: Programming Language :: Python :: 3.9
Classifier: Programming Language :: Python :: 3.10
Classifier: Programming Language :: Python :: 3.11
Classifier: Operating System :: MacOS
Classifier: Operating System :: MacOS :: MacOS X
Classifier: Operating System :: Microsoft :: Windows
Classifier: Operating System :: Microsoft :: Windows :: Windows 10
Classifier: Operating System :: Microsoft :: Windows :: Windows 11
Classifier: Operating System :: POSIX :: Linux
Requires-Python: >=3.8
License-File: LICENSE.txt
Requires-Dist: diveplane-reactor-api (==6.5.9)
Requires-Dist: certifi
